basic_auth_middleware.py
basic_auth_middleware-1.0.3.dist-info/DESCRIPTION.rst
basic_auth_middleware-1.0.3.dist-info/METADATA
basic_auth_middleware-1.0.3.dist-info/RECORD
basic_auth_middleware-1.0.3.dist-info/WHEEL
basic_auth_middleware-1.0.3.dist-info/metadata.json
basic_auth_middleware-1.0.3.dist-info/top_level.txt
