Metadata-Version: 2.0
Name: basic-auth-middleware
Version: 1.0.3
Summary: A WSGI middleware providing HTTP Basic Auth
Home-page: https://github.com/unit9/basic-auth-middleware
Author: UNIT9
Author-email: root@unit9.com
License: MIT
Platform: UNKNOWN
Classifier: Development Status :: 5 - Production/Stable
Classifier: License :: OSI Approved :: MIT License
Classifier: Programming Language :: Python :: 2
Classifier: Programming Language :: Python :: 3
Requires-Dist: netaddr (>=0.7.19)
